{
   "player_list": [
      {
         "username": "un2",
         "profile": {
            "avatar": null,
            "nickname": null,
            "fullname": null,
            "get_img_src": false
         },
         "color": "lime"
      },
      {
         "username": "un1",
         "profile": {
            "avatar": "https://localhost:3113/./src_auth/public/uploads/3.png",
            "nickname": "honghung123",
            "fullname": null,
            "get_img_src": true
         },
         "color": "lime"
      }
   ],
   "online_list": [
      "un2",
      "un1"
   ],
   "rank_list": [
      {
         "username": "un2",
         "score": 100
      }
   ]
}